aiba_hello_world/__init__.py
aiba_hello_world-0.2.dist-info/LICENSE
aiba_hello_world-0.2.dist-info/METADATA
aiba_hello_world-0.2.dist-info/WHEEL
aiba_hello_world-0.2.dist-info/top_level.txt
aiba_hello_world-0.2.dist-info/RECORD
