Metadata-Version: 2.1
Name: aiba_hello_world
Version: 0.2
Summary: Hello world test package for pypi
Home-page: https://github.com/yourusername/your_package
Author: Aiba B
Author-email: test@test.com
License: MIT
Classifier: Programming Language :: Python :: 3
Classifier: License :: OSI Approved :: MIT License
Classifier: Operating System :: OS Independent
License-File: LICENSE
